{
  "start_msg": "Привет, выбери свой город.",
  "failed_start_msg": "Укажи правильно город.",
  "representation_msg": "Укажи тип представления.",
  "failed_representation_msg": "Укажи правильный тип представления.",
  "brest": "Брест",
  "main_menu": "Главное меню.",
  "photo": "Фото",
  "text": "Текст",
  "get_updates": "Получить новые записи.",
  "settings": "Настройки.",
  "about_project": "O проекте.",
  "new_posts": "<b>Время: </b>{time} \n<b>Сообщение: </b>{message} \n\n",
  "no_posts": "Новых постов нету.",
  "settings_menu": "Выбери что хочешь настроить.",
  "settings_city": "Город",
  "settings_representation": "Представление",
  "settings_number_of_posts": "Количество постов",
  "back": "Назад",
  "settings_city_msg": "Выбери город.",
  "settings_representation_msg": "Выбери представление.",
  "settings_number_of_posts_msg": "Выбери количество постов.",
  "number_of_posts": [5, 10, 15, 20, 25, 30],
  "photo_no_support": "Фото в данный момент не поддерживается.",
  "spam_limit": "Достигнут лимит количества сообщений",
  "failed_settings": "Ты указали не правильные данные."
}